LICENSE.txt
MANIFEST.in
README.rst
ez_setup.py
setup.py
docs/simserver.rst
docs/similarities/simserver.rst
simserver/__init__.py
simserver/run_simserver.py
simserver/simserver.py
simserver.egg-info/PKG-INFO
simserver.egg-info/SOURCES.txt
simserver.egg-info/dependency_links.txt
simserver.egg-info/not-zip-safe
simserver.egg-info/requires.txt
simserver.egg-info/top_level.txt
simserver/test/__init__.py
simserver/test/test_simserver.py