Metadata-Version: 1.0
Name: simserver
Version: 0.1.4
Summary: Document similarity server
Home-page: https://github.com/piskvorky/gensim-simserver
Author: Radim Rehurek
Author-email: radimrehurek@seznam.cz
License: AGPL v3
Download-URL: http://pypi.python.org/pypi/simserver
Keywords: Similarity server,document database,Latent Semantic Indexing,LSA,LSI,LDA,Latent Dirichlet Allocation,TF-IDF,gensim
Platform: any
Classifier: Development Status :: 4 - Beta
Classifier: Environment :: Console
Classifier: Intended Audience :: Science/Research
Classifier: License :: OSI Approved :: GNU Library or Lesser General Public License (LGPL)
Classifier: Operating System :: OS Independent
Classifier: Programming Language :: Python :: 2.5
Classifier: Topic :: Scientific/Engineering :: Artificial Intelligence
Classifier: Topic :: Scientific/Engineering :: Information Analysis
Classifier: Topic :: Text Processing :: Linguistic
